.gitignore
.travis.yml
LICENSE
MANIFEST.in
README.rst
runtests.py
setup.py
DjangoDav.egg-info/PKG-INFO
DjangoDav.egg-info/SOURCES.txt
DjangoDav.egg-info/dependency_links.txt
DjangoDav.egg-info/not-zip-safe
DjangoDav.egg-info/requires.txt
DjangoDav.egg-info/top_level.txt
djangodav/__init__.py
djangodav/acls.py
djangodav/locks.py
djangodav/models.py
djangodav/responses.py
djangodav/utils.py
djangodav/auth/__init__.py
djangodav/auth/rest.py
djangodav/auth/tasty.py
djangodav/auth/tests.py
djangodav/base/__init__.py
djangodav/base/locks.py
djangodav/base/resources.py
djangodav/base/tests/__init__.py
djangodav/base/tests/resources.py
djangodav/base/tests/tests.py
djangodav/db/__init__.py
djangodav/db/resources.py
djangodav/fs/__init__.py
djangodav/fs/resources.py
djangodav/fs/tests.py
djangodav/templates/djangodav/index.html
djangodav/views/__init__.py
djangodav/views/tests.py
djangodav/views/views.py
docs/auth.rst
docs/classes.rst
docs/difference.rst
docs/howto.rst
docs/known_issues.rst
docs/motivation.rst
samples/__init__.py
samples/manage.py
samples/requirements.txt
samples/settings.py
samples/urls.py
samples/auth/__init__.py
samples/auth/views/__init__.py
samples/auth/views/rest.py
samples/auth/views/tasty.py
samples/db/__init__.py
samples/db/models.py
samples/db/resources.py
samples/fs/__init__.py
samples/fs/models.py
samples/fs/resources.py
samples/fs/views.py